banner/__init__.py
banner/admin.py
banner/apps.py
banner/models.py
banner/tests.py
banner/views.py
banner/locale/zh_Hans/LC_MESSAGES/django.mo
banner/locale/zh_Hans/LC_MESSAGES/django.po
django_banner-0.3.3.dist-info/DESCRIPTION.rst
django_banner-0.3.3.dist-info/METADATA
django_banner-0.3.3.dist-info/RECORD
django_banner-0.3.3.dist-info/WHEEL
django_banner-0.3.3.dist-info/metadata.json
django_banner-0.3.3.dist-info/top_level.txt
